starrysky/__init__.py
starrysky/getinfo.py
starrysky-0.0.1.dist-info/METADATA
starrysky-0.0.1.dist-info/WHEEL
starrysky-0.0.1.dist-info/top_level.txt
starrysky-0.0.1.dist-info/RECORD
