Metadata-Version: 2.1
Name: starrysky
Version: 0.0.1
Summary: This is me xiajibaxiede
Home-page: https://github.com/sunjian-github/ezface
Author: Jikecheng
Author-email: chengtengdazsg@163.com
License: UNKNOWN
Platform: UNKNOWN
